odoo/addons/base_domain_inverse_function/README.rst
odoo/addons/base_domain_inverse_function/__init__.py
odoo/addons/base_domain_inverse_function/__manifest__.py
odoo/addons/base_domain_inverse_function/inverse_expression.py
odoo/addons/base_domain_inverse_function/i18n/base_domain_inverse_function.pot
odoo/addons/base_domain_inverse_function/readme/CONTRIBUTORS.rst
odoo/addons/base_domain_inverse_function/readme/DESCRIPTION.rst
odoo/addons/base_domain_inverse_function/readme/ROADMAP.rst
odoo/addons/base_domain_inverse_function/readme/USAGE.rst
odoo/addons/base_domain_inverse_function/static/description/icon.png
odoo/addons/base_domain_inverse_function/static/description/index.html
odoo/addons/base_domain_inverse_function/tests/__init__.py
odoo/addons/base_domain_inverse_function/tests/test_inverse_function.py
odoo/addons/base_domain_inverse_function/tests/test_partner_domains.py
odoo13_addon_base_domain_inverse_function-13.0.1.0.1.dev4.dist-info/METADATA
odoo13_addon_base_domain_inverse_function-13.0.1.0.1.dev4.dist-info/WHEEL
odoo13_addon_base_domain_inverse_function-13.0.1.0.1.dev4.dist-info/top_level.txt
odoo13_addon_base_domain_inverse_function-13.0.1.0.1.dev4.dist-info/RECORD
